Workbook

Sheet Hypothèses
A1: PorteàPorte — Hypothèses (modifie les cases bleues)
A3: — FRAIS STRIPE —
A4: Stripe — taux (%) | B4: 0.029
A5: Stripe — frais fixe ($/transaction) | B5: 0.3
A6: Stripe Connect — taux versement (%) | B6: 0.0025
A7: Stripe Connect — frais fixe ($/versement) | B7: 0.25
A8: Stripe Connect — $/mois par compte actif | B8: 2
A10: — LIVRAISON —
A11: Ticket moyen livraison ($) | B11: 15
A12: Part livreur (%) | B12: 0.6
A14: — COVOITURAGE —
A15: Frais plateforme fixe ($/siège) | B15: 1.5 | C15: Par paliers : 1,50 $ si <15 $, 3 $ si >=15 $
A16: Ticket moyen siège ($) | B16: 25
A18: — COÛTS FIXES MENSUELS —
A19: Vercel | B19: 20
A20: Supabase | B20: 34
A21: SendGrid (courriels) | B21: 20
A22: Domaine | B22: 2
A23: Assurance responsabilité (lissée/mois) | B23: 100
A24: Paie fondateur souhaitée (/mois) | B24: 0 | C24: 0 pour l instant (Denis a un emploi) - a ajuster dans 1-2 ans
A26: Total coûts fixes (hors Connect & fondateur) | B26: =SUM(B19:B23)

Sheet Par transaction
A1: Marge réelle par transaction
A3: 📦 LIVRAISON
A4: Prix payé par le client | B4: =Hypothèses!B11
A5: Part livreur | B5: =B4*Hypothèses!B12
A6: Reste plateforme (commission brute) | B6: =B4-B5
A7: – Frais Stripe (paiement) | B7: =B4*Hypothèses!B4+Hypothèses!B5
A8: – Frais Connect (versement livreur) | B8: =B5*Hypothèses!B6+Hypothèses!B7
A9: =NET réel plateforme | B9: =B6-B7-B8
A10: Marge nette (% du prix) | B10: =B9/B4
A13: 🚗 COVOITURAGE (1 siège)
A14: Prix payé par le passager | B14: =Hypothèses!B16
A15: Frais plateforme (fixe) | B15: =Hypothèses!B15
A16: Montant au conducteur | B16: =B14-B15
A17: – Frais Stripe (paiement) | B17: =B14*Hypothèses!B4+Hypothèses!B5
A18: – Frais Connect (versement) | B18: =B16*Hypothèses!B6+Hypothèses!B7
A19: =NET réel plateforme | B19: =B15-B17-B18
A20: Marge nette (% du prix) | B20: =B19/B14

Sheet Scénarios
A1: Rentabilité mensuelle — 3 scénarios (livraison)
B3: Petit | C3: Moyen | D3: Grand
A4: Nb livraisons / mois | B4: 50 | C4: 500 | D4: 5000
A5: Nb livreurs actifs | B5: 10 | C5: 60 | D5: 400
A6: Revenu brut livraisons | B6: =B4*Hypothèses!$B$11 | C6: =C4*Hypothèses!$B$11 | D6: =D4*Hypothèses!$B$11
A7: NET plateforme (livraisons) | B7: =B4*'Par transaction'!$B$9 | C7: =C4*'Par transaction'!$B$9 | D7: =D4*'Par transaction'!$B$9
A8: – Coûts fixes (infra + assurance) | B8: =Hypothèses!$B$26 | C8: =Hypothèses!$B$26 | D8: =Hypothèses!$B$26
A9: – Coûts Connect (comptes actifs) | B9: =B5*Hypothèses!$B$8 | C9: =C5*Hypothèses!$B$8 | D9: =D5*Hypothèses!$B$8
A10: – Paie fondateur | B10: =Hypothèses!$B$24 | C10: =Hypothèses!$B$24 | D10: =Hypothèses!$B$24
A11: =PROFIT mensuel | B11: =B7-B8-B9-B10 | C11: =C7-C8-C9-C10 | D11: =D7-D8-D9-D10
A12: =PROFIT annuel | B12: =B11*12 | C12: =C11*12 | D12: =D11*12

Sheet Répartition 40%
A1: Répartition officielle proposée (sur le prix)
A3: Poste | B3: % du prix | C3: $ sur 15 $ | D3: Note
A4: 🚗 Livreur québécois | B4: 0.6 | C4: =B4*Hypothèses!$B$11 | D4: base 60 %, jusquà 70 % avec bonus
A5: 💳 Frais Stripe (réel) | B5: 0.07 | C5: =B5*Hypothèses!$B$11 | D5: coût de paiement
A6: 🔧 Infra + développement | B6: 0.05 | C6: =B6*Hypothèses!$B$11 | D6: Vercel, Supabase, dev
A7: 🛡️ Protection + urgence | B7: 0.16 | C7: =B7*Hypothèses!$B$11 | D7: sécurité d abord
A8: 💚 Communauté | B8: 0.05 | C8: =B8*Hypothèses!$B$11 | D8: organismes (pour l instant)
A9: 💪 Réserve / pérennité | B9: 0.07 | C9: =B9*Hypothèses!$B$11 | D9: réinvestissement
A10: TOTAL (doit = 100 %) | B10: =SUM(B4:B9) | C10: =SUM(C4:C9) | D10: réinvestissement
